{
  "project_info": {
    "project_number": "694235029596",
    "project_id": "ha-tv-notif",
    "storage_bucket": "ha-tv-notif.firebasestorage.app"
  },
  "client": [
    {
      "client_info": {
        "mobilesdk_app_id": "1:694235029596:android:753482f1c930b639a20699",
        "android_client_info": {
          "package_name": "com.hanotif.tv"
        }
      },
      "oauth_client": [],
      "api_key": [
        {
          "current_key": "AIzaSyCFw3OQXBP87zFZEFc-jmLOXB1WlRHMgwU"
        }
      ],
      "services": {
        "appinvite_service": {
          "other_platform_oauth_client": []
        }
      }
    }
  ],
  "configuration_version": "1"
}